LICENSE
README.md
setup.py
CVE_2021_24917.egg-info/PKG-INFO
CVE_2021_24917.egg-info/SOURCES.txt
CVE_2021_24917.egg-info/dependency_links.txt
CVE_2021_24917.egg-info/entry_points.txt
CVE_2021_24917.egg-info/requires.txt
CVE_2021_24917.egg-info/top_level.txt
cve202124917/__init__.py
cve202124917/main.py
cve202124917/includes/__init__.py
cve202124917/includes/bot.py
cve202124917/includes/filereader.py
cve202124917/includes/scan.py
cve202124917/includes/writefile.py
cve202124917/utils/__init__.py
cve202124917/utils/configure.py
cve202124917/utils/const.py
cve202124917/utils/helpers.py
cve202124917/utils/status.py